mltp/.DS_Store
mltp/__init__.py
mltp/logic_utils.py
mltp/predicates/.DS_Store
mltp/predicates/__init__.py
mltp/predicates/completeness.py
mltp/predicates/deduction.py
mltp/predicates/functions.py
mltp/predicates/operators.py
mltp/predicates/prenex.py
mltp/predicates/proofs.py
mltp/predicates/prover.py
mltp/predicates/semantics.py
mltp/predicates/some_proofs.py
mltp/predicates/syntax.py
mltp/propositions/.DS_Store
mltp/propositions/__init__.py
mltp/propositions/axiomatic_systems.py
mltp/propositions/deduction.py
mltp/propositions/operators.py
mltp/propositions/proofs.py
mltp/propositions/reductions.py
mltp/propositions/semantics.py
mltp/propositions/some_proofs.py
mltp/propositions/soundness.py
mltp/propositions/syntax.py
mltp/propositions/tautology.py
mltp-0.1.0.dist-info/licenses/LICENSE
mltp-0.1.0.dist-info/WHEEL
mltp-0.1.0.dist-info/METADATA
mltp-0.1.0.dist-info/RECORD
